[
{"title": "Dabi", "url": "https://characterprofile.fandom.com/wiki/Dabi"},
{"title": "Canti", "url": "https://characterprofile.fandom.com/wiki/Canti"},
{"title": "Carr", "url": "https://characterprofile.fandom.com/wiki/Carr"},
{"title": "Caster Leonardo da Vinci", "url": "https://characterprofile.fandom.com/wiki/Caster_Leonardo_da_Vinci"},
{"title": "Caster Medea", "url": "https://characterprofile.fandom.com/wiki/Caster_Medea"},
{"title": "Category:Danganronpa", "url": "https://characterprofile.fandom.com/wiki/Category:Danganronpa"},
{"title": "David Martinez", "url": "https://characterprofile.fandom.com/wiki/David_Martinez"},
{"title": "Category:Deadman Wonderland", "url": "https://characterprofile.fandom.com/wiki/Category:Deadman_Wonderland"},
{"title": "Death the Kid", "url": "https://characterprofile.fandom.com/wiki/Death_the_Kid"},
{"title": "Deek Slasky", "url": "https://characterprofile.fandom.com/wiki/Deek_Slasky"},
{"title": "Deep Sea King", "url": "https://characterprofile.fandom.com/wiki/Deep_Sea_King"},
{"title": "Deidara", "url": "https://characterprofile.fandom.com/wiki/Deidara"},
{"title": "Deishuu Kaiki", "url": "https://characterprofile.fandom.com/wiki/Deishuu_Kaiki"},
{"title": "Denji (Chainsaw Man)", "url": "https://characterprofile.fandom.com/wiki/Denji_(Chainsaw_Man)"},
{"title": "Diamond (Pokémon Adventures)", "url": "https://characterprofile.fandom.com/wiki/Diamond_(Pok%C3%A9mon_Adventures)"},
{"title": "Diavolo", "url": "https://characterprofile.fandom.com/wiki/Diavolo"},
{"title": "Diego Brando", "url": "https://characterprofile.fandom.com/wiki/Diego_Brando"},
{"title": "Dio Brando", "url": "https://characterprofile.fandom.com/wiki/Dio_Brando"},
{"title": "Cell", "url": "https://characterprofile.fandom.com/wiki/Cell"},
{"title": "Charlotte Katakuri", "url": "https://characterprofile.fandom.com/wiki/Charlotte_Katakuri"},
{"title": "Charlotte Pudding", "url": "https://characterprofile.fandom.com/wiki/Charlotte_Pudding"},
{"title": "Chi-Chi", "url": "https://characterprofile.fandom.com/wiki/Chi-Chi"},
{"title": "Chizome Akaguro (Stain)", "url": "https://characterprofile.fandom.com/wiki/Chizome_Akaguro_(Stain)"},
{"title": "Choplin Sukegawa", "url": "https://characterprofile.fandom.com/wiki/Choplin_Sukegawa"},
{"title": "Chris Thorndyke", "url": "https://characterprofile.fandom.com/wiki/Chris_Thorndyke"},
{"title": "Chrollo Lucilfer", "url": "https://characterprofile.fandom.com/wiki/Chrollo_Lucilfer"},
{"title": "Courier", "url": "https://characterprofile.fandom.com/wiki/Courier"},
{"title": "Coyote Starrk", "url": "https://characterprofile.fandom.com/wiki/Coyote_Starrk"},
{"title": "Creed Diskenth", "url": "https://characterprofile.fandom.com/wiki/Creed_Diskenth"},
{"title": "Crocodile (One Piece)", "url": "https://characterprofile.fandom.com/wiki/Crocodile_(One_Piece)"},
{"title": "Crona Gorgon", "url": "https://characterprofile.fandom.com/wiki/Crona_Gorgon"},
{"title": "Category:Crunchyroll", "url": "https://characterprofile.fandom.com/wiki/Category:Crunchyroll"},
{"title": "A-Ko Magami", "url": "https://characterprofile.fandom.com/wiki/A-Ko_Magami"},
{"title": "Afro Samurai (character)", "url": "https://characterprofile.fandom.com/wiki/Afro_Samurai_(character)"},
{"title": "Agumon (Adventure)", "url": "https://characterprofile.fandom.com/wiki/Agumon_(Adventure)"},
{"title": "Agumon (Data Squad)", "url": "https://characterprofile.fandom.com/wiki/Agumon_(Data_Squad)"},
{"title": "Akame", "url": "https://characterprofile.fandom.com/wiki/Akame"},
{"title": "Category:Akame ga Kill!", "url": "https://characterprofile.fandom.com/wiki/Category:Akame_ga_Kill!"},
{"title": "Category:Akudama Drive", "url": "https://characterprofile.fandom.com/wiki/Category:Akudama_Drive"},
{"title": "Alexander Anderson", "url": "https://characterprofile.fandom.com/wiki/Alexander_Anderson"},
{"title": "Gaara", "url": "https://characterprofile.fandom.com/wiki/Gaara"},
{"title": "Gabumon", "url": "https://characterprofile.fandom.com/wiki/Gabumon"},
{"title": "Gallantmon", "url": "https://characterprofile.fandom.com/wiki/Gallantmon"},
{"title": "Ganta Igarashi", "url": "https://characterprofile.fandom.com/wiki/Ganta_Igarashi"},
{"title": "Gao Mikado", "url": "https://characterprofile.fandom.com/wiki/Gao_Mikado"},
{"title": "Doctor", "url": "https://characterprofile.fandom.com/wiki/Doctor"},
{"title": "Doctor Wheelo", "url": "https://characterprofile.fandom.com/wiki/Doctor_Wheelo"},
{"title": "Doma", "url": "https://characterprofile.fandom.com/wiki/Doma"},
{"title": "Don Krieg", "url": "https://characterprofile.fandom.com/wiki/Don_Krieg"},
{"title": "Donquixote Doflamingo", "url": "https://characterprofile.fandom.com/wiki/Donquixote_Doflamingo"},
{"title": "Doraemon", "url": "https://characterprofile.fandom.com/wiki/Doraemon"},
{"title": "Dracule Mihawk", "url": "https://characterprofile.fandom.com/wiki/Dracule_Mihawk"},
{"title": "Durham Glaster", "url": "https://characterprofile.fandom.com/wiki/Durham_Glaster"},
{"title": "Eathes", "url": "https://characterprofile.fandom.com/wiki/Eathes"},
{"title": "Echidna Parass", "url": "https://characterprofile.fandom.com/wiki/Echidna_Parass"},
{"title": "Edward Elric", "url": "https://characterprofile.fandom.com/wiki/Edward_Elric"},
{"title": "Edward Newgate", "url": "https://characterprofile.fandom.com/wiki/Edward_Newgate"},
{"title": "Hacker (Akudama Drive)", "url": "https://characterprofile.fandom.com/wiki/Hacker_(Akudama_Drive)"},
{"title": "Hagire Rinichiro", "url": "https://characterprofile.fandom.com/wiki/Hagire_Rinichiro"},
{"title": "Haku", "url": "https://characterprofile.fandom.com/wiki/Haku"},
{"title": "Hatsune Miku", "url": "https://characterprofile.fandom.com/wiki/Hatsune_Miku"},
{"title": "Hawkmon", "url": "https://characterprofile.fandom.com/wiki/Hawkmon"},
{"title": "Category:Hellsing", "url": "https://characterprofile.fandom.com/wiki/Category:Hellsing"},
{"title": "Crust", "url": "https://characterprofile.fandom.com/wiki/Crust"},
{"title": "Cutthroat", "url": "https://characterprofile.fandom.com/wiki/Cutthroat"},
{"title": "All For One", "url": "https://characterprofile.fandom.com/wiki/All_For_One"},
{"title": "Alucard (Hellsing)", "url": "https://characterprofile.fandom.com/wiki/Alucard_(Hellsing)"},
{"title": "Android 13", "url": "https://characterprofile.fandom.com/wiki/Android_13"},
{"title": "Android 17", "url": "https://characterprofile.fandom.com/wiki/Android_17"},
{"title": "Android 18", "url": "https://characterprofile.fandom.com/wiki/Android_18"},
{"title": "Ann Takamaki", "url": "https://characterprofile.fandom.com/wiki/Ann_Takamaki"},
{"title": "Arbormon", "url": "https://characterprofile.fandom.com/wiki/Arbormon"},
{"title": "Archer (Fate/stay night)", "url": "https://characterprofile.fandom.com/wiki/Archer_(Fate/stay_night)"},
{"title": "Archer Oda Nobunaga", "url": "https://characterprofile.fandom.com/wiki/Archer_Oda_Nobunaga"},
{"title": "Arlong", "url": "https://characterprofile.fandom.com/wiki/Arlong"},
{"title": "Armadillomon", "url": "https://characterprofile.fandom.com/wiki/Armadillomon"},
{"title": "Arsène Lupin III", "url": "https://characterprofile.fandom.com/wiki/Ars%C3%A8ne_Lupin_III"},
{"title": "Category:Fairy Tail", "url": "https://characterprofile.fandom.com/wiki/Category:Fairy_Tail"},
{"title": "Fake Assassin", "url": "https://characterprofile.fandom.com/wiki/Fake_Assassin"},
{"title": "Falcomon", "url": "https://characterprofile.fandom.com/wiki/Falcomon"},
{"title": "Father (Fullmetal Alchemist)", "url": "https://characterprofile.fandom.com/wiki/Father_(Fullmetal_Alchemist)"},
{"title": "Feitan", "url": "https://characterprofile.fandom.com/wiki/Feitan"},
{"title": "Category:FLCL", "url": "https://characterprofile.fandom.com/wiki/Category:FLCL"},
{"title": "Foo Fighters", "url": "https://characterprofile.fandom.com/wiki/Foo_Fighters"},
{"title": "Gaomon", "url": "https://characterprofile.fandom.com/wiki/Gaomon"},
{"title": "Gatomon", "url": "https://characterprofile.fandom.com/wiki/Gatomon"},
{"title": "Genos", "url": "https://characterprofile.fandom.com/wiki/Genos"},
{"title": "Ghiaccio", "url": "https://characterprofile.fandom.com/wiki/Ghiaccio"},
{"title": "Gido (Hunter × Hunter)", "url": "https://characterprofile.fandom.com/wiki/Gido_(Hunter_%C3%97_Hunter)"},
{"title": "Gilgamesh", "url": "https://characterprofile.fandom.com/wiki/Gilgamesh"},
{"title": "Gin (One Piece)", "url": "https://characterprofile.fandom.com/wiki/Gin_(One_Piece)"},
{"title": "Category:Gintama", "url": "https://characterprofile.fandom.com/wiki/Category:Gintama"},
{"title": "Gintoki Sakata", "url": "https://characterprofile.fandom.com/wiki/Gintoki_Sakata"},
{"title": "Giorno Giovanna", "url": "https://characterprofile.fandom.com/wiki/Giorno_Giovanna"},
{"title": "God Gundam", "url": "https://characterprofile.fandom.com/wiki/God_Gundam"},
{"title": "Goemon Ishikawa XIII", "url": "https://characterprofile.fandom.com/wiki/Goemon_Ishikawa_XIII"},
{"title": "Gogeta", "url": "https://characterprofile.fandom.com/wiki/Gogeta"},
{"title": "Goku (Dragon Ball)", "url": "https://characterprofile.fandom.com/wiki/Goku_(Dragon_Ball)"},
{"title": "Goku Black", "url": "https://characterprofile.fandom.com/wiki/Goku_Black"},
{"title": "Gomamon", "url": "https://characterprofile.fandom.com/wiki/Gomamon"},
{"title": "Gon (Gon)", "url": "https://characterprofile.fandom.com/wiki/Gon_(Gon)"},
{"title": "Baam", "url": "https://characterprofile.fandom.com/wiki/Baam"},
{"title": "Baraggan Louisenbairn", "url": "https://characterprofile.fandom.com/wiki/Baraggan_Louisenbairn"},
{"title": "Category:Beelzebub", "url": "https://characterprofile.fandom.com/wiki/Category:Beelzebub"},
{"title": "Beerus", "url": "https://characterprofile.fandom.com/wiki/Beerus"},
{"title": "Belldandy", "url": "https://characterprofile.fandom.com/wiki/Belldandy"},
{"title": "Berserker Heracles", "url": "https://characterprofile.fandom.com/wiki/Berserker_Heracles"},
{"title": "Berserker Lancelot", "url": "https://characterprofile.fandom.com/wiki/Berserker_Lancelot"},
{"title": "Eijiro Kirishima (Red Riot)", "url": "https://characterprofile.fandom.com/wiki/Eijiro_Kirishima_(Red_Riot)"},
{"title": "Eijirou Kirishima", "url": "https://characterprofile.fandom.com/wiki/Eijirou_Kirishima"},
{"title": "Endou Mamoru", "url": "https://characterprofile.fandom.com/wiki/Endou_Mamoru"},
{"title": "Enel", "url": "https://characterprofile.fandom.com/wiki/Enel"},
{"title": "Enrico Pucci", "url": "https://characterprofile.fandom.com/wiki/Enrico_Pucci"},
{"title": "Eren Yeager", "url": "https://characterprofile.fandom.com/wiki/Eren_Yeager"},
{"title": "Ermes Costello", "url": "https://characterprofile.fandom.com/wiki/Ermes_Costello"},
{"title": "Erza Scarlet", "url": "https://characterprofile.fandom.com/wiki/Erza_Scarlet"},
{"title": "Esdeath", "url": "https://characterprofile.fandom.com/wiki/Esdeath"},
{"title": "Esidisi", "url": "https://characterprofile.fandom.com/wiki/Esidisi"},
{"title": "Etemon", "url": "https://characterprofile.fandom.com/wiki/Etemon"},
{"title": "Evangelion Unit-01", "url": "https://characterprofile.fandom.com/wiki/Evangelion_Unit-01"},
{"title": "Evangelion Unit-02", "url": "https://characterprofile.fandom.com/wiki/Evangelion_Unit-02"},
{"title": "Execution Division Apprentice", "url": "https://characterprofile.fandom.com/wiki/Execution_Division_Apprentice"},
{"title": "Execution Division Master", "url": "https://characterprofile.fandom.com/wiki/Execution_Division_Master"},
{"title": "Hercule Satan", "url": "https://characterprofile.fandom.com/wiki/Hercule_Satan"},
{"title": "Hibana Daida", "url": "https://characterprofile.fandom.com/wiki/Hibana_Daida"},
{"title": "Hibiki Tachibana", "url": "https://characterprofile.fandom.com/wiki/Hibiki_Tachibana"},
{"title": "Hiei", "url": "https://characterprofile.fandom.com/wiki/Hiei"},
{"title": "Hikaru and Akane", "url": "https://characterprofile.fandom.com/wiki/Hikaru_and_Akane"},
{"title": "Hinata Hyūga", "url": "https://characterprofile.fandom.com/wiki/Hinata_Hy%C5%ABga"},
{"title": "Hisoka Morow", "url": "https://characterprofile.fandom.com/wiki/Hisoka_Morow"},
{"title": "File:Hisoka.webp", "url": "https://characterprofile.fandom.com/wiki/File:Hisoka.webp"},
{"title": "Hitagi Senjougahara", "url": "https://characterprofile.fandom.com/wiki/Hitagi_Senjougahara"},
{"title": "Hol Horse", "url": "https://characterprofile.fandom.com/wiki/Hol_Horse"},
{"title": "Homura Akemi", "url": "https://characterprofile.fandom.com/wiki/Homura_Akemi"},
{"title": "Hoodlum", "url": "https://characterprofile.fandom.com/wiki/Hoodlum"},
{"title": "Category:Hunter × Hunter", "url": "https://characterprofile.fandom.com/wiki/Category:Hunter_%C3%97_Hunter"},
{"title": "Arukenimon", "url": "https://characterprofile.fandom.com/wiki/Arukenimon"},
{"title": "Ash Ketchum", "url": "https://characterprofile.fandom.com/wiki/Ash_Ketchum"},
{"title": "Asta", "url": "https://characterprofile.fandom.com/wiki/Asta"},
{"title": "Astro Boy", "url": "https://characterprofile.fandom.com/wiki/Astro_Boy"},
{"title": "Atsuko Kagari", "url": "https://characterprofile.fandom.com/wiki/Atsuko_Kagari"},
{"title": "Category:Attack on Titan", "url": "https://characterprofile.fandom.com/wiki/Category:Attack_on_Titan"},
{"title": "Aura Michibane", "url": "https://characterprofile.fandom.com/wiki/Aura_Michibane"},
{"title": "Franky", "url": "https://characterprofile.fandom.com/wiki/Franky"},
{"title": "Frieza", "url": "https://characterprofile.fandom.com/wiki/Frieza"},
{"title": "Fujitora", "url": "https://characterprofile.fandom.com/wiki/Fujitora"},
{"title": "Category:Fullmetal Alchemist", "url": "https://characterprofile.fandom.com/wiki/Category:Fullmetal_Alchemist"},
{"title": "Funny Valentine", "url": "https://characterprofile.fandom.com/wiki/Funny_Valentine"},
{"title": "Gon Freecss", "url": "https://characterprofile.fandom.com/wiki/Gon_Freecss"},
{"title": "Gouketsu", "url": "https://characterprofile.fandom.com/wiki/Gouketsu"},
{"title": "Gray Fullbuster", "url": "https://characterprofile.fandom.com/wiki/Gray_Fullbuster"},
{"title": "Greed (Fullmetal Alchemist)", "url": "https://characterprofile.fandom.com/wiki/Greed_(Fullmetal_Alchemist)"},
{"title": "Guido Mista", "url": "https://characterprofile.fandom.com/wiki/Guido_Mista"},
{"title": "Guilmon", "url": "https://characterprofile.fandom.com/wiki/Guilmon"},
{"title": "Gunbuster", "url": "https://characterprofile.fandom.com/wiki/Gunbuster"},
{"title": "Category:Gundam", "url": "https://characterprofile.fandom.com/wiki/Category:Gundam"},
{"title": "Gundam Epyon", "url": "https://characterprofile.fandom.com/wiki/Gundam_Epyon"},
{"title": "Gunkan", "url": "https://characterprofile.fandom.com/wiki/Gunkan"},
{"title": "Gurren Lagann", "url": "https://characterprofile.fandom.com/wiki/Gurren_Lagann"},
{"title": "Guts", "url": "https://characterprofile.fandom.com/wiki/Guts"},
{"title": "Gyro Zeppeli", "url": "https://characterprofile.fandom.com/wiki/Gyro_Zeppeli"},
{"title": "Biyomon", "url": "https://characterprofile.fandom.com/wiki/Biyomon"},
{"title": "Category:Black Cat", "url": "https://characterprofile.fandom.com/wiki/Category:Black_Cat"},
{"title": "BlackWarGreymon", "url": "https://characterprofile.fandom.com/wiki/BlackWarGreymon"},
{"title": "Blast (One Punch Man)", "url": "https://characterprofile.fandom.com/wiki/Blast_(One_Punch_Man)"},
{"title": "Category:Bleach", "url": "https://characterprofile.fandom.com/wiki/Category:Bleach"},
{"title": "Blossom (PPGZ)", "url": "https://characterprofile.fandom.com/wiki/Blossom_(PPGZ)"},
{"title": "Category:Bobobo-bo Bo-bobo", "url": "https://characterprofile.fandom.com/wiki/Category:Bobobo-bo_Bo-bobo"},
{"title": "Bobobo-bo Bo-bobo (character)", "url": "https://characterprofile.fandom.com/wiki/Bobobo-bo_Bo-bobo_(character)"},
{"title": "Bonolenov", "url": "https://characterprofile.fandom.com/wiki/Bonolenov"},
{"title": "Brago", "url": "https://characterprofile.fandom.com/wiki/Brago"},
{"title": "Brawler", "url": "https://characterprofile.fandom.com/wiki/Brawler"},
{"title": "Broly (Broly Trilogy)", "url": "https://characterprofile.fandom.com/wiki/Broly_(Broly_Trilogy)"},
{"title": "Broly (DBS)", "url": "https://characterprofile.fandom.com/wiki/Broly_(DBS)"},
{"title": "Brook", "url": "https://characterprofile.fandom.com/wiki/Brook"},
{"title": "Jango (One Piece)", "url": "https://characterprofile.fandom.com/wiki/Jango_(One_Piece)"},
{"title": "Ichigo Kurosaki", "url": "https://characterprofile.fandom.com/wiki/Ichigo_Kurosaki"},
{"title": "Idaki Hitara", "url": "https://characterprofile.fandom.com/wiki/Idaki_Hitara"},
{"title": "Iggy", "url": "https://characterprofile.fandom.com/wiki/Iggy"},
{"title": "Ikazuchi Akatsuki", "url": "https://characterprofile.fandom.com/wiki/Ikazuchi_Akatsuki"},
{"title": "Impmon", "url": "https://characterprofile.fandom.com/wiki/Impmon"},
{"title": "Category:InuYasha", "url": "https://characterprofile.fandom.com/wiki/Category:InuYasha"},
{"title": "Inuyasha (Character)", "url": "https://characterprofile.fandom.com/wiki/Inuyasha_(Character)"},
{"title": "Iria (Zeiram Zone)", "url": "https://characterprofile.fandom.com/wiki/Iria_(Zeiram_Zone)"},
{"title": "Category:Kadokawa Shoten", "url": "https://characterprofile.fandom.com/wiki/Category:Kadokawa_Shoten"},
{"title": "L (Death Note)", "url": "https://characterprofile.fandom.com/wiki/L_(Death_Note)"},
{"title": "Lagann", "url": "https://characterprofile.fandom.com/wiki/Lagann"},
{"title": "Lalah Sune", "url": "https://characterprofile.fandom.com/wiki/Lalah_Sune"},
{"title": "Machi", "url": "https://characterprofile.fandom.com/wiki/Machi"},
{"title": "Nagato Uzumaki", "url": "https://characterprofile.fandom.com/wiki/Nagato_Uzumaki"},
{"title": "Bruford", "url": "https://characterprofile.fandom.com/wiki/Bruford"},
{"title": "Bruno Bucciarati", "url": "https://characterprofile.fandom.com/wiki/Bruno_Bucciarati"},
{"title": "Bulma", "url": "https://characterprofile.fandom.com/wiki/Bulma"},
{"title": "Obito Uchiha", "url": "https://characterprofile.fandom.com/wiki/Obito_Uchiha"},
{"title": "Ochaco Uraraka", "url": "https://characterprofile.fandom.com/wiki/Ochaco_Uraraka"},
{"title": "Okuyasu Nijimura", "url": "https://characterprofile.fandom.com/wiki/Okuyasu_Nijimura"},
{"title": "Category:One Piece", "url": "https://characterprofile.fandom.com/wiki/Category:One_Piece"},
{"title": "Category:One Punch Man", "url": "https://characterprofile.fandom.com/wiki/Category:One_Punch_Man"},
{"title": "Orm", "url": "https://characterprofile.fandom.com/wiki/Orm"},
{"title": "Paildramon", "url": "https://characterprofile.fandom.com/wiki/Paildramon"},
{"title": "Pakunoda", "url": "https://characterprofile.fandom.com/wiki/Pakunoda"},
{"title": "Pannacotta Fugo", "url": "https://characterprofile.fandom.com/wiki/Pannacotta_Fugo"},
{"title": "Panty Anarachy", "url": "https://characterprofile.fandom.com/wiki/Panty_Anarachy"},
{"title": "Category:Parasyte", "url": "https://characterprofile.fandom.com/wiki/Category:Parasyte"},
{"title": "Patamon", "url": "https://characterprofile.fandom.com/wiki/Patamon"},
{"title": "Pearl (Pokémon Adventures)", "url": "https://characterprofile.fandom.com/wiki/Pearl_(Pok%C3%A9mon_Adventures)"},
{"title": "Jean Pierre Polnareff", "url": "https://characterprofile.fandom.com/wiki/Jean_Pierre_Polnareff"},
{"title": "Jewelry Bonney", "url": "https://characterprofile.fandom.com/wiki/Jewelry_Bonney"},
{"title": "Jibanyan", "url": "https://characterprofile.fandom.com/wiki/Jibanyan"},
{"title": "Jiraiya", "url": "https://characterprofile.fandom.com/wiki/Jiraiya"},
{"title": "Jiren", "url": "https://characterprofile.fandom.com/wiki/Jiren"},
{"title": "Johngalli A", "url": "https://characterprofile.fandom.com/wiki/Johngalli_A"},
{"title": "Johnny Joestar", "url": "https://characterprofile.fandom.com/wiki/Johnny_Joestar"},
{"title": "Category:JoJo's Bizarre Adventure", "url": "https://characterprofile.fandom.com/wiki/Category:JoJo%27s_Bizarre_Adventure"},
{"title": "Jolyne Cujoh", "url": "https://characterprofile.fandom.com/wiki/Jolyne_Cujoh"},
{"title": "Jonathan Joestar", "url": "https://characterprofile.fandom.com/wiki/Jonathan_Joestar"},
{"title": "Joseph Joestar", "url": "https://characterprofile.fandom.com/wiki/Joseph_Joestar"},
{"title": "Josuke Higashikata (Part 4)", "url": "https://characterprofile.fandom.com/wiki/Josuke_Higashikata_(Part_4)"},
{"title": "Josuke Higashikata (Part 8)", "url": "https://characterprofile.fandom.com/wiki/Josuke_Higashikata_(Part_8)"},
{"title": "Jotaro Kujo", "url": "https://characterprofile.fandom.com/wiki/Jotaro_Kujo"},
{"title": "Judar", "url": "https://characterprofile.fandom.com/wiki/Judar"},
{"title": "Irisviel von Einzbern", "url": "https://characterprofile.fandom.com/wiki/Irisviel_von_Einzbern"},
{"title": "Iron-Masked Marauder", "url": "https://characterprofile.fandom.com/wiki/Iron-Masked_Marauder"},
{"title": "Itachi Uchiha", "url": "https://characterprofile.fandom.com/wiki/Itachi_Uchiha"},
{"title": "Iwao Oguro (Knuckleduster)", "url": "https://characterprofile.fandom.com/wiki/Iwao_Oguro_(Knuckleduster)"},
{"title": "Izuko Gaen", "url": "https://characterprofile.fandom.com/wiki/Izuko_Gaen"},
{"title": "Izuku Midoriya (Deku)", "url": "https://characterprofile.fandom.com/wiki/Izuku_Midoriya_(Deku)"},
{"title": "Kaguya Ōtsutsuki", "url": "https://characterprofile.fandom.com/wiki/Kaguya_%C5%8Ctsutsuki"},
{"title": "Kakashi Hatake", "url": "https://characterprofile.fandom.com/wiki/Kakashi_Hatake"},
{"title": "Kalluto Zoldyck", "url": "https://characterprofile.fandom.com/wiki/Kalluto_Zoldyck"},
{"title": "Kamina", "url": "https://characterprofile.fandom.com/wiki/Kamina"},
{"title": "Kars", "url": "https://characterprofile.fandom.com/wiki/Kars"},
{"title": "Kastro", "url": "https://characterprofile.fandom.com/wiki/Kastro"},
{"title": "Kazuki Muto", "url": "https://characterprofile.fandom.com/wiki/Kazuki_Muto"},
{"title": "Kazuma Kuwabara", "url": "https://characterprofile.fandom.com/wiki/Kazuma_Kuwabara"},
{"title": "Kazuma Torisuna", "url": "https://characterprofile.fandom.com/wiki/Kazuma_Torisuna"},
{"title": "Kefla", "url": "https://characterprofile.fandom.com/wiki/Kefla"},
{"title": "Kenpachi Zaraki", "url": "https://characterprofile.fandom.com/wiki/Kenpachi_Zaraki"},
{"title": "Kenshiro", "url": "https://characterprofile.fandom.com/wiki/Kenshiro"},
{"title": "Keroro", "url": "https://characterprofile.fandom.com/wiki/Keroro"},
{"title": "Kevin Mask", "url": "https://characterprofile.fandom.com/wiki/Kevin_Mask"},
{"title": "Kuhn Aguero Agnes", "url": "https://characterprofile.fandom.com/wiki/Kuhn_Aguero_Agnes"},
{"title": "Kibutsuji Muzan", "url": "https://characterprofile.fandom.com/wiki/Kibutsuji_Muzan"},
{"title": "Category:Kill la Kill", "url": "https://characterprofile.fandom.com/wiki/Category:Kill_la_Kill"},
{"title": "Killua Zoldyck", "url": "https://characterprofile.fandom.com/wiki/Killua_Zoldyck"},
{"title": "Kimeramon", "url": "https://characterprofile.fandom.com/wiki/Kimeramon"},
{"title": "King (The Seven Deadly Sins)", "url": "https://characterprofile.fandom.com/wiki/King_(The_Seven_Deadly_Sins)"},
{"title": "Category:King Records", "url": "https://characterprofile.fandom.com/wiki/Category:King_Records"},
{"title": "Leon Elliot", "url": "https://characterprofile.fandom.com/wiki/Leon_Elliot"},
{"title": "Leone", "url": "https://characterprofile.fandom.com/wiki/Leone"},
{"title": "Leone Abbacchio", "url": "https://characterprofile.fandom.com/wiki/Leone_Abbacchio"},
{"title": "Light Yagami", "url": "https://characterprofile.fandom.com/wiki/Light_Yagami"},
{"title": "Lin Shaolee", "url": "https://characterprofile.fandom.com/wiki/Lin_Shaolee"},
{"title": "Lina Inverse", "url": "https://characterprofile.fandom.com/wiki/Lina_Inverse"},
{"title": "Ling Yao", "url": "https://characterprofile.fandom.com/wiki/Ling_Yao"},
{"title": "Lord Boros", "url": "https://characterprofile.fandom.com/wiki/Lord_Boros"},
{"title": "Lord Slug", "url": "https://characterprofile.fandom.com/wiki/Lord_Slug"},
{"title": "Lordgenome", "url": "https://characterprofile.fandom.com/wiki/Lordgenome"},
{"title": "Lucy (Elfen Lied)", "url": "https://characterprofile.fandom.com/wiki/Lucy_(Elfen_Lied)"},
{"title": "Lucy Heartfilia", "url": "https://characterprofile.fandom.com/wiki/Lucy_Heartfilia"},
{"title": "Madara Uchiha", "url": "https://characterprofile.fandom.com/wiki/Madara_Uchiha"},
{"title": "Category:Madhouse", "url": "https://characterprofile.fandom.com/wiki/Category:Madhouse"},
{"title": "Mai Sakurajima", "url": "https://characterprofile.fandom.com/wiki/Mai_Sakurajima"},
{"title": "Maka Albarn", "url": "https://characterprofile.fandom.com/wiki/Maka_Albarn"},
{"title": "Makoto Shishio", "url": "https://characterprofile.fandom.com/wiki/Makoto_Shishio"},
{"title": "Mami Tomoe", "url": "https://characterprofile.fandom.com/wiki/Mami_Tomoe"},
{"title": "Mantaro Muscle", "url": "https://characterprofile.fandom.com/wiki/Mantaro_Muscle"},
{"title": "Master Roshi", "url": "https://characterprofile.fandom.com/wiki/Master_Roshi"},
{"title": "Matsukaze Tenma", "url": "https://characterprofile.fandom.com/wiki/Matsukaze_Tenma"},
{"title": "Medaka Kurokami", "url": "https://characterprofile.fandom.com/wiki/Medaka_Kurokami"},
{"title": "Meicoomon", "url": "https://characterprofile.fandom.com/wiki/Meicoomon"},
{"title": "Meliodas", "url": "https://characterprofile.fandom.com/wiki/Meliodas"},
{"title": "Meruem", "url": "https://characterprofile.fandom.com/wiki/Meruem"},
{"title": "Metabee", "url": "https://characterprofile.fandom.com/wiki/Metabee"},
{"title": "Might Guy", "url": "https://characterprofile.fandom.com/wiki/Might_Guy"},
{"title": "Mikasa Ackerman", "url": "https://characterprofile.fandom.com/wiki/Mikasa_Ackerman"},
{"title": "Minato Namikaze", "url": "https://characterprofile.fandom.com/wiki/Minato_Namikaze"},
{"title": "Nagi Kengamine", "url": "https://characterprofile.fandom.com/wiki/Nagi_Kengamine"},
{"title": "Nami (One Piece)", "url": "https://characterprofile.fandom.com/wiki/Nami_(One_Piece)"},
{"title": "Naomi Misora", "url": "https://characterprofile.fandom.com/wiki/Naomi_Misora"},
{"title": "Narancia Ghirga", "url": "https://characterprofile.fandom.com/wiki/Narancia_Ghirga"},
{"title": "Narciso Anasui", "url": "https://characterprofile.fandom.com/wiki/Narciso_Anasui"},
{"title": "Category:Naruto", "url": "https://characterprofile.fandom.com/wiki/Category:Naruto"},
{"title": "Naruto Uzumaki", "url": "https://characterprofile.fandom.com/wiki/Naruto_Uzumaki"},
{"title": "Natsu Dragneel", "url": "https://characterprofile.fandom.com/wiki/Natsu_Dragneel"},
{"title": "Necro Macro", "url": "https://characterprofile.fandom.com/wiki/Necro_Macro"},
{"title": "Neferpitou", "url": "https://characterprofile.fandom.com/wiki/Neferpitou"},
{"title": "Nejire Hado (Nejire Chan)", "url": "https://characterprofile.fandom.com/wiki/Nejire_Hado_(Nejire_Chan)"},
{"title": "Category:Neon Genesis Evangelion", "url": "https://characterprofile.fandom.com/wiki/Category:Neon_Genesis_Evangelion"},
{"title": "Nezuko Kamado", "url": "https://characterprofile.fandom.com/wiki/Nezuko_Kamado"},
{"title": "Nicholas D. Wolfwood", "url": "https://characterprofile.fandom.com/wiki/Nicholas_D._Wolfwood"},
{"title": "Nico Robin", "url": "https://characterprofile.fandom.com/wiki/Nico_Robin"},
{"title": "Nnoitra Gilga", "url": "https://characterprofile.fandom.com/wiki/Nnoitra_Gilga"},
{"title": "Nomu", "url": "https://characterprofile.fandom.com/wiki/Nomu"},
{"title": "Noriaki Kakyoin", "url": "https://characterprofile.fandom.com/wiki/Noriaki_Kakyoin"},
{"title": "Noriko Takaya", "url": "https://characterprofile.fandom.com/wiki/Noriko_Takaya"},
{"title": "Perona", "url": "https://characterprofile.fandom.com/wiki/Perona"},
{"title": "Pesci", "url": "https://characterprofile.fandom.com/wiki/Pesci"},
{"title": "Pet Shop", "url": "https://characterprofile.fandom.com/wiki/Pet_Shop"},
{"title": "Petelgeuse Romanee-Conti", "url": "https://characterprofile.fandom.com/wiki/Petelgeuse_Romanee-Conti"},
{"title": "Piccolo", "url": "https://characterprofile.fandom.com/wiki/Piccolo"},
{"title": "Pikachu", "url": "https://characterprofile.fandom.com/wiki/Pikachu"},
{"title": "Pip Bernadotte", "url": "https://characterprofile.fandom.com/wiki/Pip_Bernadotte"},
{"title": "Platinum Berlitz", "url": "https://characterprofile.fandom.com/wiki/Platinum_Berlitz"},
{"title": "Portgas D. Ace", "url": "https://characterprofile.fandom.com/wiki/Portgas_D._Ace"},
{"title": "Prosciutto", "url": "https://characterprofile.fandom.com/wiki/Prosciutto"},
{"title": "Category:Puella Magi Madoka Magica", "url": "https://characterprofile.fandom.com/wiki/Category:Puella_Magi_Madoka_Magica"},
{"title": "Kirby", "url": "https://characterprofile.fandom.com/wiki/Kirby"},
{"title": "Kirito", "url": "https://characterprofile.fandom.com/wiki/Kirito"},
{"title": "Kortopi", "url": "https://characterprofile.fandom.com/wiki/Kortopi"},
{"title": "Kranz Maduke", "url": "https://characterprofile.fandom.com/wiki/Kranz_Maduke"},
{"title": "Krillin", "url": "https://characterprofile.fandom.com/wiki/Krillin"},
{"title": "Kunio", "url": "https://characterprofile.fandom.com/wiki/Kunio"},
{"title": "Kurama (Yu Yu Hakusho)", "url": "https://characterprofile.fandom.com/wiki/Kurama_(Yu_Yu_Hakusho)"},
{"title": "Kurapika", "url": "https://characterprofile.fandom.com/wiki/Kurapika"},
{"title": "Kuro (One Piece)", "url": "https://characterprofile.fandom.com/wiki/Kuro_(One_Piece)"},
{"title": "Kyoko Kirisaki (Black Cat)", "url": "https://characterprofile.fandom.com/wiki/Kyoko_Kirisaki_(Black_Cat)"},
{"title": "Kyoko Sakura", "url": "https://characterprofile.fandom.com/wiki/Kyoko_Sakura"},
{"title": "Kūgo Ginjō", "url": "https://characterprofile.fandom.com/wiki/K%C5%ABgo_Ginj%C5%8D"},
{"title": "Minatsuki Takami", "url": "https://characterprofile.fandom.com/wiki/Minatsuki_Takami"},
{"title": "Mine", "url": "https://characterprofile.fandom.com/wiki/Mine"},
{"title": "Misa Amane", "url": "https://characterprofile.fandom.com/wiki/Misa_Amane"},
{"title": "Misaka Mikoto", "url": "https://characterprofile.fandom.com/wiki/Misaka_Mikoto"},
{"title": "Category:Mob Psycho 100", "url": "https://characterprofile.fandom.com/wiki/Category:Mob_Psycho_100"},
{"title": "Monet", "url": "https://characterprofile.fandom.com/wiki/Monet"},
{"title": "Monkey D. Luffy", "url": "https://characterprofile.fandom.com/wiki/Monkey_D._Luffy"},
{"title": "Muhammad Avdol", "url": "https://characterprofile.fandom.com/wiki/Muhammad_Avdol"},
{"title": "My Hero Academia", "url": "https://characterprofile.fandom.com/wiki/My_Hero_Academia"},
{"title": "Category:My Hero Academia", "url": "https://characterprofile.fandom.com/wiki/Category:My_Hero_Academia"},
{"title": "Quilge Opie", "url": "https://characterprofile.fandom.com/wiki/Quilge_Opie"},
{"title": "Raditz", "url": "https://characterprofile.fandom.com/wiki/Raditz"},
{"title": "Ram (Re:Zero kara Hajimeru Isekai Seikatsu)", "url": "https://characterprofile.fandom.com/wiki/Ram_(Re:Zero_kara_Hajimeru_Isekai_Seikatsu)"},
{"title": "Ramba Ral", "url": "https://characterprofile.fandom.com/wiki/Ramba_Ral"},
{"title": "Ranma Saotome", "url": "https://characterprofile.fandom.com/wiki/Ranma_Saotome"},
{"title": "Category:Re:Zero kara Hajimeru Isekai Seikatsu", "url": "https://characterprofile.fandom.com/wiki/Category:Re:Zero_kara_Hajimeru_Isekai_Seikatsu"},
{"title": "Saber", "url": "https://characterprofile.fandom.com/wiki/Saber"},
{"title": "Sadaso", "url": "https://characterprofile.fandom.com/wiki/Sadaso"},
{"title": "Takuya Kanbara", "url": "https://characterprofile.fandom.com/wiki/Takuya_Kanbara"},
{"title": "Ulquiorra Cifer", "url": "https://characterprofile.fandom.com/wiki/Ulquiorra_Cifer"},
{"title": "Rem", "url": "https://characterprofile.fandom.com/wiki/Rem"},
{"title": "Renamon", "url": "https://characterprofile.fandom.com/wiki/Renamon"},
{"title": "Renji Abarai", "url": "https://characterprofile.fandom.com/wiki/Renji_Abarai"},
{"title": "Rider Medusa", "url": "https://characterprofile.fandom.com/wiki/Rider_Medusa"},
{"title": "Rin Tohsaka", "url": "https://characterprofile.fandom.com/wiki/Rin_Tohsaka"},
{"title": "River Zastory", "url": "https://characterprofile.fandom.com/wiki/River_Zastory"},
{"title": "Rob Lucci", "url": "https://characterprofile.fandom.com/wiki/Rob_Lucci"},
{"title": "Robert E. O. Speedwagon", "url": "https://characterprofile.fandom.com/wiki/Robert_E._O._Speedwagon"},
{"title": "Robonyan", "url": "https://characterprofile.fandom.com/wiki/Robonyan"},
{"title": "Rock Lee", "url": "https://characterprofile.fandom.com/wiki/Rock_Lee"},
{"title": "Roronoa Zoro", "url": "https://characterprofile.fandom.com/wiki/Roronoa_Zoro"},
{"title": "Rouge the Bat", "url": "https://characterprofile.fandom.com/wiki/Rouge_the_Bat"},
{"title": "Roy Mustang", "url": "https://characterprofile.fandom.com/wiki/Roy_Mustang"},
{"title": "Sailor Moon (character)", "url": "https://characterprofile.fandom.com/wiki/Sailor_Moon_(character)"},
{"title": "Saitama", "url": "https://characterprofile.fandom.com/wiki/Saitama"},
{"title": "Sakura Kinomoto", "url": "https://characterprofile.fandom.com/wiki/Sakura_Kinomoto"},
{"title": "Sandman (JoJo's Bizarre Adventure)", "url": "https://characterprofile.fandom.com/wiki/Sandman_(JoJo%27s_Bizarre_Adventure)"},
{"title": "Sanji", "url": "https://characterprofile.fandom.com/wiki/Sanji"},
{"title": "Sasori", "url": "https://characterprofile.fandom.com/wiki/Sasori"},
{"title": "Sasuke Uchiha", "url": "https://characterprofile.fandom.com/wiki/Sasuke_Uchiha"},
{"title": "Satsuki Kiryūin", "url": "https://characterprofile.fandom.com/wiki/Satsuki_Kiry%C5%ABin"},
{"title": "Sayaka Miki", "url": "https://characterprofile.fandom.com/wiki/Sayaka_Miki"},
{"title": "Sephiria Arks", "url": "https://characterprofile.fandom.com/wiki/Sephiria_Arks"},
{"title": "Seras Victoria", "url": "https://characterprofile.fandom.com/wiki/Seras_Victoria"},
{"title": "Sesshōmaru", "url": "https://characterprofile.fandom.com/wiki/Sessh%C5%8Dmaru"},
{"title": "Shaiapouf", "url": "https://characterprofile.fandom.com/wiki/Shaiapouf"},
{"title": "Shigekiyo Yangu", "url": "https://characterprofile.fandom.com/wiki/Shigekiyo_Yangu"},
{"title": "Shigeo Kageyama", "url": "https://characterprofile.fandom.com/wiki/Shigeo_Kageyama"},
{"title": "Shinichi Izumi", "url": "https://characterprofile.fandom.com/wiki/Shinichi_Izumi"},
{"title": "Shirou Emiya", "url": "https://characterprofile.fandom.com/wiki/Shirou_Emiya"},
{"title": "Shizuku", "url": "https://characterprofile.fandom.com/wiki/Shizuku"},
{"title": "Shooting Star and Black Viper", "url": "https://characterprofile.fandom.com/wiki/Shooting_Star_and_Black_Viper"},
{"title": "Shoto Todoroki (Shoto)", "url": "https://characterprofile.fandom.com/wiki/Shoto_Todoroki_(Shoto)"},
{"title": "Shouta Aizawa (Eraser Head)", "url": "https://characterprofile.fandom.com/wiki/Shouta_Aizawa_(Eraser_Head)"},
{"title": "Tanjiro Kamado", "url": "https://characterprofile.fandom.com/wiki/Tanjiro_Kamado"},
{"title": "Tashigi", "url": "https://characterprofile.fandom.com/wiki/Tashigi"},
{"title": "Tatsumaki", "url": "https://characterprofile.fandom.com/wiki/Tatsumaki"},
{"title": "Tatsumi", "url": "https://characterprofile.fandom.com/wiki/Tatsumi"},
{"title": "Tatsumi Oga", "url": "https://characterprofile.fandom.com/wiki/Tatsumi_Oga"},
{"title": "Category:Tengen Toppa Gurren Lagann", "url": "https://characterprofile.fandom.com/wiki/Category:Tengen_Toppa_Gurren_Lagann"},
{"title": "Tengen Toppa Gurren Lagann (character)", "url": "https://characterprofile.fandom.com/wiki/Tengen_Toppa_Gurren_Lagann_(character)"},
{"title": "Tentomon", "url": "https://characterprofile.fandom.com/wiki/Tentomon"},
{"title": "Terriermon", "url": "https://characterprofile.fandom.com/wiki/Terriermon"},
{"title": "Terry Bogard", "url": "https://characterprofile.fandom.com/wiki/Terry_Bogard"},
{"title": "Teruki Hanazawa", "url": "https://characterprofile.fandom.com/wiki/Teruki_Hanazawa"},
{"title": "Tetsuo Shima", "url": "https://characterprofile.fandom.com/wiki/Tetsuo_Shima"},
{"title": "The Anti-Spiral", "url": "https://characterprofile.fandom.com/wiki/The_Anti-Spiral"},
{"title": "Category:The Seven Deadly Sins", "url": "https://characterprofile.fandom.com/wiki/Category:The_Seven_Deadly_Sins"},
{"title": "The Speaker (Vividred Operation)", "url": "https://characterprofile.fandom.com/wiki/The_Speaker_(Vividred_Operation)"},
{"title": "Thorfinn", "url": "https://characterprofile.fandom.com/wiki/Thorfinn"},
{"title": "Tokiko Tsumura", "url": "https://characterprofile.fandom.com/wiki/Tokiko_Tsumura"},
{"title": "Category:Top wo Nerae! Gunbuster", "url": "https://characterprofile.fandom.com/wiki/Category:Top_wo_Nerae!_Gunbuster"},
{"title": "Toriko", "url": "https://characterprofile.fandom.com/wiki/Toriko"},
{"title": "Toshinori Yagi (All Might)", "url": "https://characterprofile.fandom.com/wiki/Toshinori_Yagi_(All_Might)"},
{"title": "Trafalgar Law", "url": "https://characterprofile.fandom.com/wiki/Trafalgar_Law"},
{"title": "Category:Ultimate Muscle", "url": "https://characterprofile.fandom.com/wiki/Category:Ultimate_Muscle"},
{"title": "Uryū Ishida", "url": "https://characterprofile.fandom.com/wiki/Ury%C5%AB_Ishida"},
{"title": "Usopp", "url": "https://characterprofile.fandom.com/wiki/Usopp"},
{"title": "Uta (One Piece)", "url": "https://characterprofile.fandom.com/wiki/Uta_(One_Piece)"},
{"title": "Uzume Sumeragi", "url": "https://characterprofile.fandom.com/wiki/Uzume_Sumeragi"},
{"title": "Valt Aoi", "url": "https://characterprofile.fandom.com/wiki/Valt_Aoi"},
{"title": "Wakaba Saegusa", "url": "https://characterprofile.fandom.com/wiki/Wakaba_Saegusa"},
{"title": "Walter C. Dornez", "url": "https://characterprofile.fandom.com/wiki/Walter_C._Dornez"},
{"title": "Wammu", "url": "https://characterprofile.fandom.com/wiki/Wammu"},
{"title": "Weather Report", "url": "https://characterprofile.fandom.com/wiki/Weather_Report"},
{"title": "Yadamon", "url": "https://characterprofile.fandom.com/wiki/Yadamon"},
{"title": "Yamato (One Piece)", "url": "https://characterprofile.fandom.com/wiki/Yamato_(One_Piece)"},
{"title": "Yami Yugi", "url": "https://characterprofile.fandom.com/wiki/Yami_Yugi"},
{"title": "Yang Xiao Long", "url": "https://characterprofile.fandom.com/wiki/Yang_Xiao_Long"},
{"title": "Yellow", "url": "https://characterprofile.fandom.com/wiki/Yellow"},
{"title": "Yoko Littner", "url": "https://characterprofile.fandom.com/wiki/Yoko_Littner"},
{"title": "Ruby Rose", "url": "https://characterprofile.fandom.com/wiki/Ruby_Rose"},
{"title": "RX-78-2 Gundam", "url": "https://characterprofile.fandom.com/wiki/RX-78-2_Gundam"},
{"title": "Ryūko Matoi", "url": "https://characterprofile.fandom.com/wiki/Ry%C5%ABko_Matoi"},
{"title": "Category:Shōnen Jump", "url": "https://characterprofile.fandom.com/wiki/Category:Sh%C5%8Dnen_Jump"},
{"title": "Shūkurō Tsukishima", "url": "https://characterprofile.fandom.com/wiki/Sh%C5%ABkur%C5%8D_Tsukishima"},
{"title": "Sieg", "url": "https://characterprofile.fandom.com/wiki/Sieg"},
{"title": "Simon the Digger", "url": "https://characterprofile.fandom.com/wiki/Simon_the_Digger"},
{"title": "Sinbad", "url": "https://characterprofile.fandom.com/wiki/Sinbad"},
{"title": "Sird", "url": "https://characterprofile.fandom.com/wiki/Sird"},
{"title": "Slayer White", "url": "https://characterprofile.fandom.com/wiki/Slayer_White"},
{"title": "Smoker", "url": "https://characterprofile.fandom.com/wiki/Smoker"},
{"title": "Train Heartnet", "url": "https://characterprofile.fandom.com/wiki/Train_Heartnet"},
{"title": "Trish Una", "url": "https://characterprofile.fandom.com/wiki/Trish_Una"},
{"title": "Trunks (Future)", "url": "https://characterprofile.fandom.com/wiki/Trunks_(Future)"},
{"title": "Tsubasa Kazanari", "url": "https://characterprofile.fandom.com/wiki/Tsubasa_Kazanari"},
{"title": "Turles", "url": "https://characterprofile.fandom.com/wiki/Turles"},
{"title": "Vanilla Ice", "url": "https://characterprofile.fandom.com/wiki/Vanilla_Ice"},
{"title": "Vash the Stampede", "url": "https://characterprofile.fandom.com/wiki/Vash_the_Stampede"},
{"title": "Veemon", "url": "https://characterprofile.fandom.com/wiki/Veemon"},
{"title": "Vegeta", "url": "https://characterprofile.fandom.com/wiki/Vegeta"},
{"title": "Vegito", "url": "https://characterprofile.fandom.com/wiki/Vegito"},
{"title": "Viral", "url": "https://characterprofile.fandom.com/wiki/Viral"},
{"title": "Wedding Peach (character)", "url": "https://characterprofile.fandom.com/wiki/Wedding_Peach_(character)"},
{"title": "Wendy Marvell", "url": "https://characterprofile.fandom.com/wiki/Wendy_Marvell"},
{"title": "Wilhelm van Astrea", "url": "https://characterprofile.fandom.com/wiki/Wilhelm_van_Astrea"},
{"title": "William Anthonio Zeppeli", "url": "https://characterprofile.fandom.com/wiki/William_Anthonio_Zeppeli"},
{"title": "Wonderweiss Margela", "url": "https://characterprofile.fandom.com/wiki/Wonderweiss_Margela"},
{"title": "Wormmon", "url": "https://characterprofile.fandom.com/wiki/Wormmon"},
{"title": "Yoruichi Shihōin", "url": "https://characterprofile.fandom.com/wiki/Yoruichi_Shih%C5%8Din"},
{"title": "Yoshikage Kira", "url": "https://characterprofile.fandom.com/wiki/Yoshikage_Kira"},
{"title": "Younger Toguro", "url": "https://characterprofile.fandom.com/wiki/Younger_Toguro"},
{"title": "Category:Yu Yu Hakusho", "url": "https://characterprofile.fandom.com/wiki/Category:Yu_Yu_Hakusho"},
{"title": "Yusuke Urameshi", "url": "https://characterprofile.fandom.com/wiki/Yusuke_Urameshi"},
{"title": "Zabuza Momochi", "url": "https://characterprofile.fandom.com/wiki/Zabuza_Momochi"},
{"title": "Category:Zatch Bell!", "url": "https://characterprofile.fandom.com/wiki/Category:Zatch_Bell!"},
{"title": "Zephyr (One Piece)", "url": "https://characterprofile.fandom.com/wiki/Zephyr_(One_Piece)"},
{"title": "Zommari Rureaux", "url": "https://characterprofile.fandom.com/wiki/Zommari_Rureaux"},
{"title": "Son Gohan", "url": "https://characterprofile.fandom.com/wiki/Son_Gohan"},
{"title": "Category:Soul Eater", "url": "https://characterprofile.fandom.com/wiki/Category:Soul_Eater"},
{"title": "Soul Evans", "url": "https://characterprofile.fandom.com/wiki/Soul_Evans"},
{"title": "Speed-o'-Sound Sonic", "url": "https://characterprofile.fandom.com/wiki/Speed-o%27-Sound_Sonic"},
{"title": "Category:Stand Users", "url": "https://characterprofile.fandom.com/wiki/Category:Stand_Users"},
{"title": "Stocking Anarchy", "url": "https://characterprofile.fandom.com/wiki/Stocking_Anarchy"},
{"title": "Strider Hiryu", "url": "https://characterprofile.fandom.com/wiki/Strider_Hiryu"},
{"title": "Sven Vollfied", "url": "https://characterprofile.fandom.com/wiki/Sven_Vollfied"},
{"title": "Swindler", "url": "https://characterprofile.fandom.com/wiki/Swindler"},
{"title": "Category:Sword Art Online", "url": "https://characterprofile.fandom.com/wiki/Category:Sword_Art_Online"},
{"title": "Syaoran Li", "url": "https://characterprofile.fandom.com/wiki/Syaoran_Li"},
{"title": "Szayelaporro Grantz", "url": "https://characterprofile.fandom.com/wiki/Szayelaporro_Grantz"},
{"title": "Sōsuke Aizen", "url": "https://characterprofile.fandom.com/wiki/S%C5%8Dsuke_Aizen"},
{"title": "Yadamon", "url": "https://characterprofile.fandom.com/wiki/Yadamon"},
{"title": "Yamato (One Piece)", "url": "https://characterprofile.fandom.com/wiki/Yamato_(One_Piece)"},
{"title": "Yami Yugi", "url": "https://characterprofile.fandom.com/wiki/Yami_Yugi"},
{"title": "Yang Xiao Long", "url": "https://characterprofile.fandom.com/wiki/Yang_Xiao_Long"},
{"title": "Yellow", "url": "https://characterprofile.fandom.com/wiki/Yellow"},
{"title": "Yoko Littner", "url": "https://characterprofile.fandom.com/wiki/Yoko_Littner"},
{"title": "Yoruichi Shihōin", "url": "https://characterprofile.fandom.com/wiki/Yoruichi_Shih%C5%8Din"},
{"title": "Yoshikage Kira", "url": "https://characterprofile.fandom.com/wiki/Yoshikage_Kira"},
{"title": "Younger Toguro", "url": "https://characterprofile.fandom.com/wiki/Younger_Toguro"},
{"title": "Category:Yu Yu Hakusho", "url": "https://characterprofile.fandom.com/wiki/Category:Yu_Yu_Hakusho"},
{"title": "Yusuke Urameshi", "url": "https://characterprofile.fandom.com/wiki/Yusuke_Urameshi"},
{"title": "Zabuza Momochi", "url": "https://characterprofile.fandom.com/wiki/Zabuza_Momochi"},
{"title": "Category:Zatch Bell!", "url": "https://characterprofile.fandom.com/wiki/Category:Zatch_Bell!"},
{"title": "Zephyr (One Piece)", "url": "https://characterprofile.fandom.com/wiki/Zephyr_(One_Piece)"},
{"title": "Zommari Rureaux", "url": "https://characterprofile.fandom.com/wiki/Zommari_Rureaux"}
]